rtl/ltssm.sv
module ltssm #(
  parameter integer DETECT_WAIT_CYCLES = 2,
  parameter integer TRAIN_WAIT_CYCLES  = 2,
  parameter integer CONFIG_WAIT_CYCLES = 2,
  parameter integer RECOVERY_WAIT_CYCLES = 2
)(
  input  logic clk,
  input  logic rst_n,

  input  logic phy_rx_detected,
  input  logic training_done,
  input  logic link_width_ok,
  input  logic lane_config_ok,

  input  logic recovery_request,
  input  logic phy_error,
  input  logic disable_request,
  input  logic hot_reset_request,

  output logic link_up,
  output logic tx_enable,
  output logic rx_enable,
  output logic training_enable,
  output logic recovery_active,
  output logic [5:0] state,
  output logic state_changed
);

  localparam [5:0]
    DETECT_QUIET = 6'h00,
    DETECT_ACTIVE = 6'h01,
    POLLING_ACTIVE = 6'h02,
    POLLING_CONFIGURATION = 6'h04,
    CONFIG_LINKWIDTH_START = 6'h05,
    CONFIG_LINKWIDTH_ACCEPT = 6'h06,
    CONFIG_LANENUM_WAIT = 6'h08,
    CONFIG_LANENUM_ACCEPT = 6'h07,
    CONFIG_COMPLETE = 6'h09,
    CONFIG_IDLE = 6'h0A,
    L0 = 6'h10,
    RECOVERY = 6'h0B,
    DISABLED = 6'h20,
    HOT_RESET = 6'h27;

  logic [5:0] state_q, state_d;
  integer timer_q, timer_d;

  function automatic integer wait_cycles(input integer n);
    if (n < 1) wait_cycles = 1;
    else wait_cycles = n;
  endfunction

  always_comb begin
    state_d = state_q;
    timer_d = timer_q;

    case (state_q)
      DETECT_QUIET: begin
        timer_d = 0;
        if (disable_request) state_d = DISABLED;
        else state_d = DETECT_ACTIVE;
      end

      DETECT_ACTIVE: begin
        if (disable_request) begin state_d = DISABLED; timer_d = 0; end
        else if (hot_reset_request) begin state_d = HOT_RESET; timer_d = 0; end
        else if (phy_rx_detected) begin state_d = POLLING_ACTIVE; timer_d = 0; end
      end

      POLLING_ACTIVE: begin
        if (disable_request) begin state_d = DISABLED; timer_d = 0; end
        else if (hot_reset_request) begin state_d = HOT_RESET; timer_d = 0; end
        else if (timer_q >= wait_cycles(TRAIN_WAIT_CYCLES)-1) begin
          state_d = POLLING_CONFIGURATION; timer_d = 0;
        end else timer_d = timer_q + 1;
      end

      POLLING_CONFIGURATION: begin
        if (disable_request) begin state_d = DISABLED; timer_d = 0; end
        else if (training_done) begin state_d = CONFIG_LINKWIDTH_START; timer_d = 0; end
        else timer_d = timer_q + 1;
      end

      CONFIG_LINKWIDTH_START: begin
        if (link_width_ok) state_d = CONFIG_LINKWIDTH_ACCEPT;
      end

      CONFIG_LINKWIDTH_ACCEPT: begin
        if (lane_config_ok) state_d = CONFIG_LANENUM_WAIT;
      end

      CONFIG_LANENUM_WAIT: begin
        state_d = CONFIG_LANENUM_ACCEPT;
      end

      CONFIG_LANENUM_ACCEPT: begin
        state_d = CONFIG_COMPLETE;
      end

      CONFIG_COMPLETE: begin
        state_d = CONFIG_IDLE;
      end

      CONFIG_IDLE: begin
        if (timer_q >= wait_cycles(CONFIG_WAIT_CYCLES)-1) begin
          state_d = L0; timer_d = 0;
        end else timer_d = timer_q + 1;
      end

      L0: begin
        timer_d = 0;
        if (disable_request) state_d = DISABLED;
        else if (hot_reset_request) state_d = HOT_RESET;
        else if (recovery_request || phy_error) state_d = RECOVERY;
      end

      RECOVERY: begin
        if (disable_request) begin state_d = DISABLED; timer_d = 0; end
        else if (hot_reset_request) begin state_d = HOT_RESET; timer_d = 0; end
        else if (timer_q >= wait_cycles(RECOVERY_WAIT_CYCLES)-1) begin
          state_d = L0; timer_d = 0;
        end else timer_d = timer_q + 1;
      end

      DISABLED: begin
        timer_d = 0;
        if (hot_reset_request) state_d = HOT_RESET;
        else if (!disable_request) state_d = DETECT_QUIET;
      end

      HOT_RESET: begin
        timer_d = 0;
        if (!hot_reset_request) state_d = DETECT_QUIET;
      end

      default: begin
        state_d = DETECT_QUIET;
        timer_d = 0;
      end
    endcase
  end

  always_ff @(posedge clk or negedge rst_n) begin
    if (!rst_n) begin
      state_q <= DETECT_QUIET;
      timer_q <= 0;
    end else begin
      state_q <= state_d;
      timer_q <= timer_d;
    end
  end

  always_comb begin
    state = state_q;
    state_changed = (state_d != state_q);
    link_up = (state_q == L0);
    tx_enable = (state_q == L0);
    rx_enable = (state_q == L0) || (state_q == RECOVERY);
    training_enable = (state_q == DETECT_ACTIVE) ||
                      (state_q == POLLING_ACTIVE) ||
                      (state_q == POLLING_CONFIGURATION) ||
                      (state_q == CONFIG_LINKWIDTH_START) ||
                      (state_q == CONFIG_LINKWIDTH_ACCEPT) ||
                      (state_q == CONFIG_LANENUM_WAIT) ||
                      (state_q == CONFIG_LANENUM_ACCEPT) ||
                      (state_q == CONFIG_COMPLETE) ||
                      (state_q == CONFIG_IDLE);
    recovery_active = (state_q == RECOVERY);
  end
endmodule

tb/tb_ltssm.sv
`timescale 1ns/1ps
module tb_ltssm;
  logic clk=0, rst_n=0;
  always #5 clk=~clk;
  logic phy_rx_detected=0, training_done=0, link_width_ok=0, lane_config_ok=0;
  logic recovery_request=0, phy_error=0, disable_request=0, hot_reset_request=0;
  logic link_up,tx_enable,rx_enable,training_enable,recovery_active,state_changed;
  logic [5:0] state;
  ltssm dut(.*);
  initial begin
    $dumpfile("ltssm.vcd"); $dumpvars(0,tb_ltssm);
    repeat(3) @(posedge clk); rst_n<=1;
    @(posedge clk); phy_rx_detected<=1;
    @(posedge clk); training_done<=1; link_width_ok<=1; lane_config_ok<=1;
    repeat(15) @(posedge clk);
    if(!link_up) $fatal(1,"FAIL: LTSSM did not reach L0");
    if(tx_enable !== 1'b1 || rx_enable !== 1'b1) $fatal(1,"FAIL: L0 enables incorrect");
    $display("PASS: standalone LTSSM reached L0");
    recovery_request<=1; @(posedge clk); recovery_request<=0;
    @(posedge clk);
    if(recovery_active !== 1'b1 || tx_enable !== 1'b0) $fatal(1,"FAIL: Recovery controls");
    repeat(5) @(posedge clk);
    if(!link_up) $fatal(1,"FAIL: Recovery did not return L0");
    $display("PASS: standalone Recovery returned L0");
    disable_request<=1; repeat(2) @(posedge clk);
    if(state!==6'h20 || tx_enable!==1'b0) $fatal(1,"FAIL: Disabled state");
    disable_request<=0; repeat(2) @(posedge clk);
    if(state!==6'h00 && state!==6'h01) $fatal(1,"FAIL: Detect return");
    $display("PASS: standalone Disabled returned to Detect");
    $finish;
  end
endmodule

tb/ltssm.vcd
$date
	Mon Sep  7 05:58:33 2026
$end
$version
	Icarus Verilog
$end
$timescale
	1ps
$end
$scope module tb_ltssm $end
$var wire 1 ! tx_enable $end
$var wire 1 " training_enable $end
$var wire 1 # state_changed $end
$var wire 6 $ state [5:0] $end
$var wire 1 % rx_enable $end
$var wire 1 & recovery_active $end
$var wire 1 ' link_up $end
$var reg 1 ( clk $end
$var reg 1 ) disable_request $end
$var reg 1 * hot_reset_request $end
$var reg 1 + lane_config_ok $end
$var reg 1 , link_width_ok $end
$var reg 1 - phy_error $end
$var reg 1 . phy_rx_detected $end
$var reg 1 / recovery_request $end
$var reg 1 0 rst_n $end
$var reg 1 1 training_done $end
$scope module dut $end
$var wire 1 ( clk $end
$var wire 1 ) disable_request $end
$var wire 1 * hot_reset_request $end
$var wire 1 + lane_config_ok $end
$var wire 1 , link_width_ok $end
$var wire 1 - phy_error $end
$var wire 1 . phy_rx_detected $end
$var wire 1 / recovery_request $end
$var wire 1 0 rst_n $end
$var wire 1 1 training_done $end
$var parameter 6 2 CONFIG_COMPLETE $end
$var parameter 6 3 CONFIG_IDLE $end
$var parameter 6 4 CONFIG_LANENUM_ACCEPT $end
$var parameter 6 5 CONFIG_LANENUM_WAIT $end
$var parameter 6 6 CONFIG_LINKWIDTH_ACCEPT $end
$var parameter 6 7 CONFIG_LINKWIDTH_START $end
$var parameter 32 8 CONFIG_WAIT_CYCLES $end
$var parameter 6 9 DETECT_ACTIVE $end
$var parameter 6 : DETECT_QUIET $end
$var parameter 32 ; DETECT_WAIT_CYCLES $end
$var parameter 6 < DISABLED $end
$var parameter 6 = HOT_RESET $end
$var parameter 6 > L0 $end
$var parameter 6 ? POLLING_ACTIVE $end
$var parameter 6 @ POLLING_CONFIGURATION $end
$var parameter 6 A RECOVERY $end
$var parameter 32 B RECOVERY_WAIT_CYCLES $end
$var parameter 32 C TRAIN_WAIT_CYCLES $end
$var reg 1 ' link_up $end
$var reg 1 & recovery_active $end
$var reg 1 % rx_enable $end
$var reg 6 D state [5:0] $end
$var reg 1 # state_changed $end
$var reg 6 E state_d [5:0] $end
$var reg 6 F state_q [5:0] $end
$var reg 1 " training_enable $end
$var reg 1 ! tx_enable $end
$var integer 32 G timer_d [31:0] $end
$var integer 32 H timer_q [31:0] $end
$scope function wait_cycles $end
$upscope $end
$upscope $end
$upscope $end
$enddefinitions $end
$comment Show the parameter values. $end
$dumpall
b10 C
b10 B
b1011 A
b100 @
b10 ?
b10000 >
b100111 =
b100000 <
b10 ;
b0 :
b1 9
b10 8
b101 7
b110 6
b1000 5
b111 4
b1010 3
b1001 2
$end
#0
$dumpvars
bx H
b0 G
bx F
b0 E
bx D
01
00
0/
0.
0-
0,
0+
0*
0)
0(
x'
x&
x%
bx $
x#
x"
x!
$end
#5000
0&
0"
0%
0!
0'
1#
b0 $
b0 D
b1 E
b0 H
b0 F
1(
#10000
0(
#15000
1(
#20000
0(
#25000
10
1(
#30000
0(
#35000
1"
b1 $
b1 D
b10 E
b1 F
1.
1(
#40000
0(
#45000
0#
b10 $
b10 D
b1 G
b10 F
1+
1,
11
1(
#50000
0(
#55000
1#
b0 G
b100 E
b1 H
1(
#60000
0(
#65000
b100 $
b100 D
b101 E
b0 H
b100 F
1(
#70000
0(
#75000
b101 $
b101 D
b110 E
b101 F
1(
#80000
0(
#85000
b110 $
b110 D
b1000 E
b110 F
1(
#90000
0(
#95000
b1000 $
b1000 D
b111 E
b1000 F
1(
#100000
0(
#105000
b111 $
b111 D
b1001 E
b111 F
1(
#110000
0(
#115000
b1001 $
b1001 D
b1010 E
b1001 F
1(
#120000
0(
#125000
0#
b1010 $
b1010 D
b1 G
b1010 F
1(
#130000
0(
#135000
1#
b0 G
b10000 E
b1 H
1(
#140000
0(
#145000
0"
1%
1!
1'
0#
b10000 $
b10000 D
b0 H
b10000 F
1(
#150000
0(
#155000
1(
#160000
0(
#165000
1(
#170000
0(
#175000
1(
#180000
0(
#185000
1(
#190000
0(
#195000
1#
b1011 E
1/
1(
#200000
0(
#205000
1&
0!
0'
0#
b1011 $
b1011 D
b1 G
b1011 F
0/
1(
#210000
0(
#215000
1#
b0 G
b10000 E
b1 H
1(
#220000
0(
#225000
0&
1!
1'
0#
b10000 $
b10000 D
b0 H
b10000 F
1(
#230000
0(
#235000
1(
#240000
0(
#245000
1(
#250000
0(
#255000
1(
#260000
0(
#265000
1#
b100000 E
1)
1(
#270000
0(
#275000
0%
0!
0'
0#
b100000 $
b100000 D
b100000 F
1(
#280000
0(
#285000
1#
b0 E
0)
1(
#290000
0(
#295000
b0 $
b0 D
b1 E
b0 F
1(
#300000
0(
#305000
1"
b1 $
b1 D
b10 E
b1 F
1(
